README.md
setup.py
dao_deploy/__init__.py
dao_deploy/client.py
dao_deploy/config.py
dao_deploy/deploy.py
dao_deploy/errors.py
dao_deploy/logger.py
dao_deploy/models.py
dao_deploy.egg-info/PKG-INFO
dao_deploy.egg-info/SOURCES.txt
dao_deploy.egg-info/dependency_links.txt
dao_deploy.egg-info/requires.txt
dao_deploy.egg-info/top_level.txt