Metadata-Version: 1.1
Name: dao-deploy
Version: 0.0.8
Summary: DaoCloud Service 2.0 deploy tools
Home-page: http://www.daocloud.io
Author: DaoCloud
Author-email: hypo.chen@daocloud.io
License: UNKNOWN
Platform: UNKNOWN
Classifier: Development Status :: 3 - Alpha
Classifier: Intended Audience :: Developers
Classifier: Topic :: Software Development :: Build Tools
Classifier: Programming Language :: Python :: 3
Classifier: Programming Language :: Python :: 3.5
Classifier: Programming Language :: Python :: 3.6
